objsize/__init__.py
objsize/traverse.py
objsize-0.7.0.dist-info/LICENSE
objsize-0.7.0.dist-info/METADATA
objsize-0.7.0.dist-info/WHEEL
objsize-0.7.0.dist-info/top_level.txt
objsize-0.7.0.dist-info/RECORD
