Metadata-Version: 2.1
Name: objsize
Version: 0.7.0
Summary: Traversal over Python's objects subtree and calculate the total size of the subtree in bytes (deep size).
Author-email: Liran Funaro <liran.funaro@gmail.com>
License: BSD-3-Clause
Project-URL: Homepage, https://github.com/liran-funaro/objsize
Keywords: object-size,recursive,deep,traversal,object,size,debug,deep-object-size
Classifier: Programming Language :: Python
Classifier: Programming Language :: Python :: 3
Classifier: License :: OSI Approved :: BSD License
Classifier: Operating System :: OS Independent
Classifier: Topic :: Software Development :: Libraries :: Python Modules
Requires-Python: >=3.7
Provides-Extra: dev
Provides-Extra: docs
License-File: LICENSE
